{
    "docker": {
        "command": null,
        "detach": true,
        "entrypoint": "'/sb/bin/do_solidity.sh' '/sb/PossiblySendUserDefinedAddress.sol' '0' '/sb/bin' '0'",
        "image": "smartbugs/mythril:0.23.15",
        "user": 0,
        "volumes": {
            "C:\\Users\\Lisa\\AppData\\Local\\Temp\\tmpmq5fptg7": {
                "bind": "/sb",
                "mode": "rw"
            }
        }
    },
    "filename": "\\Users\\Lisa\\Documents\\Uni\\Diplomarbeit\\CreateBasedPossibly\\CreateBasedReentrancy\\v5\\Possibly\\Send\\UserDefinedAddress\\PossiblySendUserDefinedAddress.sol",
    "platform": {
        "cpu": "Intel(R) Core(TM) i7-9750H CPU @ 2.60GHz",
        "python": "3.10.4.final.0 (64 bit)",
        "release": "10",
        "smartbugs": "2.0.8",
        "system": "Windows",
        "version": "10.0.19045"
    },
    "result": {
        "duration": 43.576667070388794,
        "exit_code": 0,
        "logs": "result.log",
        "output": null,
        "start": 1710202507.1738188
    },
    "runid": "20240312_001505",
    "solc": "0.5.17",
    "tool": {
        "bin": "scripts",
        "command": null,
        "cpu_quota": null,
        "entrypoint": "'$BIN/do_solidity.sh' '$FILENAME' '$TIMEOUT' '$BIN' '$MAIN'",
        "id": "mythril-0.23.15",
        "image": "smartbugs/mythril:0.23.15",
        "info": "Mythril analyses EVM bytecode using symbolic analysis, taint analysis and control flow checking to detect a variety of security vulnerabilities.",
        "mem_limit": null,
        "mode": "solidity",
        "name": "Mythril",
        "origin": "https://github.com/ConsenSys/mythril",
        "output": null,
        "parser": "parser.py",
        "solc": true,
        "version": "0.23.15"
    }
}
